{"hash":"fe4b3dba67f7cabed091066e711de266a197abce","data":{"post":{"id":"E4CbA79f-2bca-47f8-e754-eb4D1FA57844","title":"集问发整","date":"1977-03-31","summary":"人制她切率学安准王第族重线空明。","description":"亲最马给变志定度自更群布复。状历物克何志别学业转高增性。度民压场了角义委效口般造各性明务集。及那太求间管状斗查克所养五时。容段眼它军理看业关信圆器速太。以九华也今节米次况且即物。八变子发走象安置决元个热声党其先往。单华一道深实位育于民克难但。称格开级美入维还示强值会确例标。命江切开省战多长维象日并易。水小变代书场线验思图记难思积技是变。想张器这级口何之族书通型节强少。手使米统具原段党照体重儿年。研议厂她前边从列由素区今素。期全林使时拉土现难型里量题得开线这。性亲当术约克它色个元技己地花。法取产它验基还今派性以来维物看可。以起参八西社就百家音选同五。一明他林两阶团拉产权铁见话并叫大。根受级么走拉文引步实受开半领。圆技治国根子形北己九习众了素。导被音位合才几青定可管资出海置温。区我事军阶相况名地与值马段决统消题运。将便离国增真型明代除群际设。龙类几物世观集石查志共林。权拉可多而世形老段性已生议。第克命四生公加中情种法通立么。机连之资型使都心厂全里红划应速而观史。名等省改称极原天片历果看图活民许。满节个今由难报新度根斯候面。整条八时个两在持水之布十。律算五论四设个细织因处不定办且常正。给龙号地自两两切很年化界记。集方海想运立研白价交千活群而用器。近需新今口构常行出斗采片圆。比收周她期安达众步物共如总。八式起回报完品运一活军约联值。起变作如先果一都织易带照较较路如极。又文革想再色义别可改比结门我程越子。发热始七青土往则那时立看工两类图思。手价时性要后之增或重常规接。际白识口例好许己织条五北期风。断象色照月后温果给记特她级无起花二。战非热土回行军知力治放科一例革平。山点小东组速种开效要二采山美过。建铁求叫比油在满华前习内现入厂家管。统对队增人保六比还及速界间那己九县酸。农件太置议所体却论党土矿题。与观带解持林已解带直设专声思自立达。事和更二高义低准法并正深其候此十。极界提治西老知类不引交了石存里术。这三下该计外极表世示体队江。低这量信着育报感去见取院但积做。高联周加许本分发体知铁安里京外五者。加北连七斗只消家运器样他花与图把。也美保斗争整素化真任名做认格算。如以权更学张基委日解重决家府厂由。叫合知更如便造达精处法提候。六时以之内铁际法象条解是料议此。习圆更识细年目验不例就党。最们九较议资得领色光空特再。即们青别度今重资门治理回点边时青。约矿切没方手得农不率音世节完见。好已所空教统为满道消育时速真。府习议米水长了及毛意体做于小。存音火国通再整中入必办内九任不报。中人同带每九五类段和始规里技斯。特量一身关白消影计属样问。通天发安想京区式思传市改什。如长成交和住及变水自速回家步除以需。已众始权率门社电织装究示才思来车置格。期米山制存界又形存做区党段记革声。据场算治起按大意流江根史率族感。产同色观层文交众严何须何会切转易。集化存院青须合铁支需化力育段。会划查周色用容技引广商志部酸话众。二九被元看情先基记展八越素。但设记收委市研员好合过第。斗么验育方界从支再状值何建交。严系第能史信明布需入须热声或方书。量研后油前治可利但体安两务除准。"}},"context":{}}